{
  "configVersion": 1,
  "timestamp": 1658744654030,
  "index": "https://drexxdk.github.io/guess-who/index.html",
  "assetGroups": [
    {
      "name": "app",
      "installMode": "prefetch",
      "updateMode": "prefetch",
      "cacheQueryOptions": {
        "ignoreVary": true
      },
      "urls": [
        "https://drexxdk.github.io/guess-who/158.30689b0466a49766.js",
        "https://drexxdk.github.io/guess-who/351.47999e7dae788f97.js",
        "https://drexxdk.github.io/guess-who/610.319aaf50dba892ea.js",
        "https://drexxdk.github.io/guess-who/assets/icons/android-chrome-192x192.png",
        "https://drexxdk.github.io/guess-who/assets/icons/android-chrome-512x512.png",
        "https://drexxdk.github.io/guess-who/assets/icons/apple-touch-icon.png",
        "https://drexxdk.github.io/guess-who/assets/icons/favicon-16x16.png",
        "https://drexxdk.github.io/guess-who/assets/icons/favicon-32x32.png",
        "https://drexxdk.github.io/guess-who/assets/icons/favicon.ico",
        "https://drexxdk.github.io/guess-who/assets/icons/safari-pinned-tab.svg",
        "https://drexxdk.github.io/guess-who/common.98636ef94d816907.js",
        "https://drexxdk.github.io/guess-who/index.html",
        "https://drexxdk.github.io/guess-who/initial.min.css",
        "https://drexxdk.github.io/guess-who/main.b8df9182e64fbf28.js",
        "https://drexxdk.github.io/guess-who/manifest.webmanifest",
        "https://drexxdk.github.io/guess-who/polyfills.637adcee7c77c591.js",
        "https://drexxdk.github.io/guess-who/runtime.6d8b17bd301e6edb.js"
      ],
      "patterns": []
    },
    {
      "name": "assets",
      "installMode": "lazy",
      "updateMode": "prefetch",
      "cacheQueryOptions": {
        "ignoreVary": true
      },
      "urls": [
        "https://drexxdk.github.io/guess-who/assets/i18n/da.json",
        "https://drexxdk.github.io/guess-who/assets/i18n/en.json",
        "https://drexxdk.github.io/guess-who/assets/people/1.webp",
        "https://drexxdk.github.io/guess-who/assets/people/2.webp",
        "https://drexxdk.github.io/guess-who/assets/people/3.webp",
        "https://drexxdk.github.io/guess-who/assets/people/4.webp",
        "https://drexxdk.github.io/guess-who/assets/people/5.webp",
        "https://drexxdk.github.io/guess-who/assets/people/6.webp",
        "https://drexxdk.github.io/guess-who/assets/people/7.webp",
        "https://drexxdk.github.io/guess-who/assets/people/8.webp",
        "https://drexxdk.github.io/guess-who/assets/svg/blank.svg",
        "https://drexxdk.github.io/guess-who/assets/svg/check.svg",
        "https://drexxdk.github.io/guess-who/assets/svg/chevron-right.svg",
        "https://drexxdk.github.io/guess-who/assets/svg/image.svg",
        "https://drexxdk.github.io/guess-who/assets/svg/ios-menu.svg",
        "https://drexxdk.github.io/guess-who/assets/svg/loading.svg",
        "https://drexxdk.github.io/guess-who/assets/svg/logo.svg",
        "https://drexxdk.github.io/guess-who/assets/svg/user.png",
        "https://drexxdk.github.io/guess-who/assets/svg/x-mark.svg"
      ],
      "patterns": []
    }
  ],
  "dataGroups": [],
  "hashTable": {
    "https://drexxdk.github.io/guess-who/158.30689b0466a49766.js": "eae235e21e97f9ab9d1099abd96476d168e1d2d0",
    "https://drexxdk.github.io/guess-who/351.47999e7dae788f97.js": "710a0b0bd907a2af437f87bc21b269d9617f03d0",
    "https://drexxdk.github.io/guess-who/610.319aaf50dba892ea.js": "dcc5181da3e13407e65cee9f03be798842e7c19f",
    "https://drexxdk.github.io/guess-who/assets/i18n/da.json": "21d61da5aca47aaa1410b17ddddb518208a0c380",
    "https://drexxdk.github.io/guess-who/assets/i18n/en.json": "aec4ea33c1c86108186583a1d8fdfb62675081b7",
    "https://drexxdk.github.io/guess-who/assets/icons/android-chrome-192x192.png": "b9349d8b8fd104e88f0d3255e0c4e6cf619d6073",
    "https://drexxdk.github.io/guess-who/assets/icons/android-chrome-512x512.png": "19652da937801c2456d6832a8c76152814684dbf",
    "https://drexxdk.github.io/guess-who/assets/icons/apple-touch-icon.png": "85fda2cba30e0f66cd3ec607c91c0476529b7a10",
    "https://drexxdk.github.io/guess-who/assets/icons/favicon-16x16.png": "237dc27415fcc1852799618c6259ae97523f258a",
    "https://drexxdk.github.io/guess-who/assets/icons/favicon-32x32.png": "e1eba7ff3b775f2a7cd9dd53a618a4b4f3e70d3d",
    "https://drexxdk.github.io/guess-who/assets/icons/favicon.ico": "cafe2b2f3a00036bee264f3de93111923ceb8b70",
    "https://drexxdk.github.io/guess-who/assets/icons/safari-pinned-tab.svg": "dfb3c581985135d7815c36bf4f7f13d30859072b",
    "https://drexxdk.github.io/guess-who/assets/people/1.webp": "90df3a35cdaada4740f5b44114fe24e07e62e848",
    "https://drexxdk.github.io/guess-who/assets/people/2.webp": "284d415899054ae8e79089689552af61ab5f33ab",
    "https://drexxdk.github.io/guess-who/assets/people/3.webp": "e7794c737b430034de5beccc8305517966564d24",
    "https://drexxdk.github.io/guess-who/assets/people/4.webp": "0c822efc1a594561b517496e66b81120eca4dd76",
    "https://drexxdk.github.io/guess-who/assets/people/5.webp": "5fb6052ee242fc9bd9eaaae75be897b2e2c80287",
    "https://drexxdk.github.io/guess-who/assets/people/6.webp": "2ab0070ed160d73fad06970ec6fbb9e0eae8cd11",
    "https://drexxdk.github.io/guess-who/assets/people/7.webp": "667acf1245233565854eb51b6e3fcf7a774d9a48",
    "https://drexxdk.github.io/guess-who/assets/people/8.webp": "030b18d2fa0a5a4b286f284f1f1643d8d63cb976",
    "https://drexxdk.github.io/guess-who/assets/svg/blank.svg": "f23e5916a5b85d8fdfe49f2cb7da6a40968352f1",
    "https://drexxdk.github.io/guess-who/assets/svg/check.svg": "41861e0943565f0901d3f8c40287e48592fc748a",
    "https://drexxdk.github.io/guess-who/assets/svg/chevron-right.svg": "19e6e8f31444fbcc0e852f14b0a8a429fa5d4c07",
    "https://drexxdk.github.io/guess-who/assets/svg/image.svg": "e718e06c16672e0f66957cb865602fcc9dc7801f",
    "https://drexxdk.github.io/guess-who/assets/svg/ios-menu.svg": "5cf097284104180692073375e263536cbcabdd5c",
    "https://drexxdk.github.io/guess-who/assets/svg/loading.svg": "f06d532f3c75cdf9e5a3eb9b65a8525e3e490919",
    "https://drexxdk.github.io/guess-who/assets/svg/logo.svg": "38ed9a0b2db5c1586f378dd970a8413dbd5b16db",
    "https://drexxdk.github.io/guess-who/assets/svg/user.png": "f9d6142dcb0d875724af039952c20dee98006de4",
    "https://drexxdk.github.io/guess-who/assets/svg/x-mark.svg": "3b7365176da8f0bfac418ad2f032fa1465248666",
    "https://drexxdk.github.io/guess-who/common.98636ef94d816907.js": "79ecb5d27cb8e80a3d0e926e7ae7796dc2fbd0ce",
    "https://drexxdk.github.io/guess-who/index.html": "8a2476f79336712701541af41e3f4c226430d7b0",
    "https://drexxdk.github.io/guess-who/initial.min.css": "5798149851497aeacec2a9a1229f5d18e210ae67",
    "https://drexxdk.github.io/guess-who/main.b8df9182e64fbf28.js": "4d490d9bbd2b00fcd8f81391fdd580085333fd64",
    "https://drexxdk.github.io/guess-who/manifest.webmanifest": "936e4b3d8b44308e66f8efe4cb5672fa446f52e8",
    "https://drexxdk.github.io/guess-who/polyfills.637adcee7c77c591.js": "ac5346e0e4e02b59de6a8acbb69d486e5ffb1f0f",
    "https://drexxdk.github.io/guess-who/runtime.6d8b17bd301e6edb.js": "763b95584d66079b07a79d3539552c5cb2ffa999"
  },
  "navigationUrls": [
    {
      "positive": true,
      "regex": "^\\/.*$"
    },
    {
      "positive": false,
      "regex": "^\\/(?:.+\\/)?[^/]*\\.[^/]*$"
    },
    {
      "positive": false,
      "regex": "^\\/(?:.+\\/)?[^/]*__[^/]*$"
    },
    {
      "positive": false,
      "regex": "^\\/(?:.+\\/)?[^/]*__[^/]*\\/.*$"
    }
  ],
  "navigationRequestStrategy": "performance"
}